binance/__init__.py
binance/client/__init__.py
binance/client/base_api.py
binance/client/historical_trades.py
binance/client/price.py
binance/domain/__init__.py
binance/domain/coin_price_limit.py
binance/domain/symbol_config.py
binance/exception/__init__.py
binance/exception/symbol_exception.py
binance/utils/__init__.py
binance/utils/decimal_util.py
binance_us_client-0.0.8.3.dist-info/LICENSE
binance_us_client-0.0.8.3.dist-info/METADATA
binance_us_client-0.0.8.3.dist-info/WHEEL
binance_us_client-0.0.8.3.dist-info/top_level.txt
binance_us_client-0.0.8.3.dist-info/RECORD
