Metadata-Version: 2.1
Name: binance-us-client
Version: 0.0.8.3
Summary: tool pkg.
Home-page: https://github.com/yromeMfOtuO/binance-us-client
Author: yromeMfOtuO
Author-email: weihao.lv@outlook.com
License: GPLv3
Platform: UNKNOWN
Classifier: Programming Language :: Python :: 3
Classifier: License :: OSI Approved :: GNU General Public License v3 (GPLv3)
Classifier: Operating System :: OS Independent
Requires-Python: >=3.6
License-File: LICENSE
Requires-Dist: setuptools ~=57.1.0
Requires-Dist: requests ~=2.25.1
